<!--
~~~~~~~~~~~~~~~~~~~~~~~~~~~~~~~~~~~~~
 Profile: [MIN] Muddy Water               
 Author: Str8_no_life                           
~~~~~~~~~~~~~~~~~~~~~~~~~~~~~~~~~~~~~
 Version: 1.0                                     
~~~~~~~~~~~~~~~~~~~~~~~~~~~~~~~~~~~~~
-->
<Profile>

	<Name>[MIN] 3+ Muddy Water (v1.0) -SNL</Name>

	<Order>			

			<While Condition="Core.Player.ClassLevel &gt; 1">
				<If Condition="not IsOnMap(141)">
					<TeleportTo Name="Black Brush Station" AetheryteId="53" />
				</If>
				
				<ExGather DiscoverUnknowns="true">
				
					<GatherObjects>
						<GatherObject>Mineral Deposit</GatherObject>
					</GatherObjects>
					
					<Items>
						<GatherItem Name="Muddy Water" />
					</Items>
					
					<HotSpots>
						<HotSpot Radius="80" XYZ="-119.3545, 3.005669, 216.4536" />
					</HotSpots>
					
				</ExGather>
			</While>

	</Order>

</Profile>
